acg/__init__.py
acg/acg.py
acg/templates/__init__.py
acg/templates/client/api_client.txt
acg/templates/client/class.txt
acg/templates/client/imports.txt
acg/templates/client/property.txt
acg/templates/client/request.txt
acg/templates/package/init.txt
acg/templates/package/license.txt
acg/templates/package/requirements.txt
acg/templates/package/setup.txt
acg/templates/pypi/pypirc.txt
acg-0.1.0.dist-info/DESCRIPTION.rst
acg-0.1.0.dist-info/METADATA
acg-0.1.0.dist-info/RECORD
acg-0.1.0.dist-info/WHEEL
acg-0.1.0.dist-info/entry_points.txt
acg-0.1.0.dist-info/metadata.json
acg-0.1.0.dist-info/top_level.txt
